README.rst
setup.py
logger_helper/__init__.py
logger_helper.egg-info/PKG-INFO
logger_helper.egg-info/SOURCES.txt
logger_helper.egg-info/dependency_links.txt
logger_helper.egg-info/top_level.txt