Metadata-Version: 1.1
Name: logger-helper
Version: 0.1.0
Summary: A simple way to gather verbose logs from your application!
Home-page: https://github.com/vimist/logger-helper
Author: Vimist
Author-email: UNKNOWN
License: UNKNOWN
Platform: UNKNOWN
Classifier: Intended Audience :: Developers
Classifier: Natural Language :: English
Classifier: Operating System :: OS Independent
Classifier: Topic :: Software Development :: Bug Tracking
Classifier: Topic :: System :: Logging
Classifier: Topic :: System :: Monitoring
